<nse-scripts>
<directory path="/usr/bin/../share/nmap/scripts/" name="scripts"></directory>
<directory path="/usr/bin/../share/nmap/nselib/" name="nselib"></directory>
<script filename="/usr/bin/../share/nmap/scripts/afp-ls.nse">
<categories><category>discovery</category><category>safe</category></categories>
<description>Attempts to get useful information about files from AFP volumes.&#xa;The output is intended to resemble the output of &lt;code&gt;ls&lt;/code&gt;.&#xa;</description>
</script>
<script filename="/usr/bin/../share/nmap/scripts/afp-serverinfo.nse">
<categories><category>default</category><category>discovery</category><category>safe</category></categories>
<description>Shows AFP server information. This information includes the server&apos;s&#xa;hostname, IPv4 and IPv6 addresses, and hardware type (for example&#xa;&lt;code&gt;Macmini&lt;/code&gt; or &lt;code&gt;MacBookPro&lt;/code&gt;).&#xa;</description>
</script>
<script filename="/usr/bin/../share/nmap/scripts/afp-showmount.nse">
<categories><category>discovery</category><category>safe</category></categories>
<description>Shows AFP shares and ACLs.&#xa;</description>
</script>
</nse-scripts>
